{
  "zero_slop_policy": {
    "statement": "NO AI SLOP ALLOWED AT ALL - ZERO TOLERANCE TO SLOP AND HALLUCINATIONS",
    "strict_compliance": "Mandatory. Every claim must be project-specific, evidence-backed, trace-linked, reviewer-challenged, and free of unsupported invention.",
    "missing_evidence_rule": "If evidence is missing, mark it as an assumption, risk, open question, or failure."
  },
  "items": [
    {
      "artifact_id": "GOV-001",
      "artifact_name": "Project Charter",
      "family": "governance-management",
      "rubric_md": "governance-management/gov-001-project-charter-rubric.md",
      "rubric_json": "governance-management/gov-001-project-charter-rubric.json",
      "artifact_level_check_count": 18,
      "critic_seat_count": 3,
      "critic_seat_check_count": 45,
      "total_check_count": 63
    },
    {
      "artifact_id": "GOV-002",
      "artifact_name": "Standards Tailoring Matrix",
      "family": "governance-management",
      "rubric_md": "governance-management/gov-002-standards-tailoring-matrix-rubric.md",
      "rubric_json": "governance-management/gov-002-standards-tailoring-matrix-rubric.json",
      "artifact_level_check_count": 18,
      "critic_seat_count": 3,
      "critic_seat_check_count": 45,
      "total_check_count": 63
    },
    {
      "artifact_id": "GOV-003",
      "artifact_name": "RASCI Matrix",
      "family": "governance-management",
      "rubric_md": "governance-management/gov-003-rasci-matrix-rubric.md",
      "rubric_json": "governance-management/gov-003-rasci-matrix-rubric.json",
      "artifact_level_check_count": 18,
      "critic_seat_count": 3,
      "critic_seat_check_count": 45,
      "total_check_count": 63
    },
    {
      "artifact_id": "GOV-004",
      "artifact_name": "Risk Register",
      "family": "governance-management",
      "rubric_md": "governance-management/gov-004-risk-register-rubric.md",
      "rubric_json": "governance-management/gov-004-risk-register-rubric.json",
      "artifact_level_check_count": 18,
      "critic_seat_count": 3,
      "critic_seat_check_count": 45,
      "total_check_count": 63
    },
    {
      "artifact_id": "GOV-005",
      "artifact_name": "Change Management Plan",
      "family": "governance-management",
      "rubric_md": "governance-management/gov-005-change-management-plan-rubric.md",
      "rubric_json": "governance-management/gov-005-change-management-plan-rubric.json",
      "artifact_level_check_count": 18,
      "critic_seat_count": 3,
      "critic_seat_check_count": 45,
      "total_check_count": 63
    },
    {
      "artifact_id": "GOV-006",
      "artifact_name": "Quality Management Plan",
      "family": "governance-management",
      "rubric_md": "governance-management/gov-006-quality-management-plan-rubric.md",
      "rubric_json": "governance-management/gov-006-quality-management-plan-rubric.json",
      "artifact_level_check_count": 18,
      "critic_seat_count": 3,
      "critic_seat_check_count": 45,
      "total_check_count": 63
    },
    {
      "artifact_id": "GOV-007",
      "artifact_name": "AI Governance Plan",
      "family": "governance-management",
      "rubric_md": "governance-management/gov-007-ai-governance-plan-rubric.md",
      "rubric_json": "governance-management/gov-007-ai-governance-plan-rubric.json",
      "artifact_level_check_count": 18,
      "critic_seat_count": 3,
      "critic_seat_check_count": 45,
      "total_check_count": 63
    },
    {
      "artifact_id": "GOV-008",
      "artifact_name": "DFMS Control Graph",
      "family": "governance-management",
      "rubric_md": "governance-management/gov-008-dfms-control-graph-rubric.md",
      "rubric_json": "governance-management/gov-008-dfms-control-graph-rubric.json",
      "artifact_level_check_count": 18,
      "critic_seat_count": 3,
      "critic_seat_check_count": 45,
      "total_check_count": 63
    },
    {
      "artifact_id": "GOV-009",
      "artifact_name": "Work Ledger Schema",
      "family": "governance-management",
      "rubric_md": "governance-management/gov-009-work-ledger-schema-rubric.md",
      "rubric_json": "governance-management/gov-009-work-ledger-schema-rubric.json",
      "artifact_level_check_count": 18,
      "critic_seat_count": 3,
      "critic_seat_check_count": 45,
      "total_check_count": 63
    },
    {
      "artifact_id": "GOV-010",
      "artifact_name": "Attractor Run Record",
      "family": "governance-management",
      "rubric_md": "governance-management/gov-010-attractor-run-record-rubric.md",
      "rubric_json": "governance-management/gov-010-attractor-run-record-rubric.json",
      "artifact_level_check_count": 18,
      "critic_seat_count": 3,
      "critic_seat_check_count": 45,
      "total_check_count": 63
    },
    {
      "artifact_id": "GOV-011",
      "artifact_name": "Methodology Blend Record",
      "family": "governance-management",
      "rubric_md": "governance-management/gov-011-methodology-blend-record-rubric.md",
      "rubric_json": "governance-management/gov-011-methodology-blend-record-rubric.json",
      "artifact_level_check_count": 18,
      "critic_seat_count": 3,
      "critic_seat_check_count": 45,
      "total_check_count": 63
    },
    {
      "artifact_id": "REQ-001",
      "artifact_name": "Business Requirements Document",
      "family": "requirements-product",
      "rubric_md": "requirements-product/req-001-business-requirements-document-rubric.md",
      "rubric_json": "requirements-product/req-001-business-requirements-document-rubric.json",
      "artifact_level_check_count": 18,
      "critic_seat_count": 3,
      "critic_seat_check_count": 45,
      "total_check_count": 63
    },
    {
      "artifact_id": "REQ-002",
      "artifact_name": "Software Requirements Specification",
      "family": "requirements-product",
      "rubric_md": "requirements-product/req-002-software-requirements-specification-rubric.md",
      "rubric_json": "requirements-product/req-002-software-requirements-specification-rubric.json",
      "artifact_level_check_count": 18,
      "critic_seat_count": 3,
      "critic_seat_check_count": 45,
      "total_check_count": 63
    },
    {
      "artifact_id": "REQ-003",
      "artifact_name": "Non-Functional Requirements Catalog",
      "family": "requirements-product",
      "rubric_md": "requirements-product/req-003-non-functional-requirements-catalog-rubric.md",
      "rubric_json": "requirements-product/req-003-non-functional-requirements-catalog-rubric.json",
      "artifact_level_check_count": 18,
      "critic_seat_count": 3,
      "critic_seat_check_count": 45,
      "total_check_count": 63
    },
    {
      "artifact_id": "REQ-004",
      "artifact_name": "Acceptance Criteria and Scenarios",
      "family": "requirements-product",
      "rubric_md": "requirements-product/req-004-acceptance-criteria-and-scenarios-rubric.md",
      "rubric_json": "requirements-product/req-004-acceptance-criteria-and-scenarios-rubric.json",
      "artifact_level_check_count": 18,
      "critic_seat_count": 3,
      "critic_seat_check_count": 45,
      "total_check_count": 63
    },
    {
      "artifact_id": "REQ-005",
      "artifact_name": "Glossary and Ubiquitous Language",
      "family": "requirements-product",
      "rubric_md": "requirements-product/req-005-glossary-and-ubiquitous-language-rubric.md",
      "rubric_json": "requirements-product/req-005-glossary-and-ubiquitous-language-rubric.json",
      "artifact_level_check_count": 18,
      "critic_seat_count": 3,
      "critic_seat_check_count": 45,
      "total_check_count": 63
    },
    {
      "artifact_id": "REQ-006",
      "artifact_name": "Assumption and Constraint Log",
      "family": "requirements-product",
      "rubric_md": "requirements-product/req-006-assumption-and-constraint-log-rubric.md",
      "rubric_json": "requirements-product/req-006-assumption-and-constraint-log-rubric.json",
      "artifact_level_check_count": 18,
      "critic_seat_count": 3,
      "critic_seat_check_count": 45,
      "total_check_count": 63
    },
    {
      "artifact_id": "REQ-007",
      "artifact_name": "Interrogation Record",
      "family": "requirements-product",
      "rubric_md": "requirements-product/req-007-interrogation-record-rubric.md",
      "rubric_json": "requirements-product/req-007-interrogation-record-rubric.json",
      "artifact_level_check_count": 18,
      "critic_seat_count": 3,
      "critic_seat_check_count": 45,
      "total_check_count": 63
    },
    {
      "artifact_id": "REQ-008",
      "artifact_name": "Spec Decomposition Record",
      "family": "requirements-product",
      "rubric_md": "requirements-product/req-008-spec-decomposition-record-rubric.md",
      "rubric_json": "requirements-product/req-008-spec-decomposition-record-rubric.json",
      "artifact_level_check_count": 18,
      "critic_seat_count": 3,
      "critic_seat_check_count": 45,
      "total_check_count": 63
    },
    {
      "artifact_id": "ARC-001",
      "artifact_name": "High-Level Design",
      "family": "architecture-design",
      "rubric_md": "architecture-design/arc-001-high-level-design-rubric.md",
      "rubric_json": "architecture-design/arc-001-high-level-design-rubric.json",
      "artifact_level_check_count": 18,
      "critic_seat_count": 3,
      "critic_seat_check_count": 45,
      "total_check_count": 63
    },
    {
      "artifact_id": "ARC-002",
      "artifact_name": "Low-Level Design",
      "family": "architecture-design",
      "rubric_md": "architecture-design/arc-002-low-level-design-rubric.md",
      "rubric_json": "architecture-design/arc-002-low-level-design-rubric.json",
      "artifact_level_check_count": 18,
      "critic_seat_count": 3,
      "critic_seat_check_count": 45,
      "total_check_count": 63
    },
    {
      "artifact_id": "ARC-003",
      "artifact_name": "Architecture Decision Records",
      "family": "architecture-design",
      "rubric_md": "architecture-design/arc-003-architecture-decision-records-rubric.md",
      "rubric_json": "architecture-design/arc-003-architecture-decision-records-rubric.json",
      "artifact_level_check_count": 18,
      "critic_seat_count": 3,
      "critic_seat_check_count": 45,
      "total_check_count": 63
    },
    {
      "artifact_id": "ARC-004",
      "artifact_name": "Interface/API Specification",
      "family": "architecture-design",
      "rubric_md": "architecture-design/arc-004-interface-api-specification-rubric.md",
      "rubric_json": "architecture-design/arc-004-interface-api-specification-rubric.json",
      "artifact_level_check_count": 18,
      "critic_seat_count": 3,
      "critic_seat_check_count": 45,
      "total_check_count": 63
    },
    {
      "artifact_id": "ARC-005",
      "artifact_name": "Data Model and Migration Plan",
      "family": "architecture-design",
      "rubric_md": "architecture-design/arc-005-data-model-and-migration-plan-rubric.md",
      "rubric_json": "architecture-design/arc-005-data-model-and-migration-plan-rubric.json",
      "artifact_level_check_count": 18,
      "critic_seat_count": 3,
      "critic_seat_check_count": 45,
      "total_check_count": 63
    },
    {
      "artifact_id": "ARC-006",
      "artifact_name": "Threat Model",
      "family": "architecture-design",
      "rubric_md": "architecture-design/arc-006-threat-model-rubric.md",
      "rubric_json": "architecture-design/arc-006-threat-model-rubric.json",
      "artifact_level_check_count": 18,
      "critic_seat_count": 3,
      "critic_seat_check_count": 45,
      "total_check_count": 63
    },
    {
      "artifact_id": "ARC-007",
      "artifact_name": "Observability Design",
      "family": "architecture-design",
      "rubric_md": "architecture-design/arc-007-observability-design-rubric.md",
      "rubric_json": "architecture-design/arc-007-observability-design-rubric.json",
      "artifact_level_check_count": 18,
      "critic_seat_count": 3,
      "critic_seat_check_count": 45,
      "total_check_count": 63
    },
    {
      "artifact_id": "MDA-001",
      "artifact_name": "Computation-Independent Model",
      "family": "mda-ddd-modeling",
      "rubric_md": "mda-ddd-modeling/mda-001-computation-independent-model-rubric.md",
      "rubric_json": "mda-ddd-modeling/mda-001-computation-independent-model-rubric.json",
      "artifact_level_check_count": 18,
      "critic_seat_count": 3,
      "critic_seat_check_count": 45,
      "total_check_count": 63
    },
    {
      "artifact_id": "MDA-002",
      "artifact_name": "Platform-Independent Model",
      "family": "mda-ddd-modeling",
      "rubric_md": "mda-ddd-modeling/mda-002-platform-independent-model-rubric.md",
      "rubric_json": "mda-ddd-modeling/mda-002-platform-independent-model-rubric.json",
      "artifact_level_check_count": 18,
      "critic_seat_count": 3,
      "critic_seat_check_count": 45,
      "total_check_count": 63
    },
    {
      "artifact_id": "MDA-003",
      "artifact_name": "Platform-Specific Model",
      "family": "mda-ddd-modeling",
      "rubric_md": "mda-ddd-modeling/mda-003-platform-specific-model-rubric.md",
      "rubric_json": "mda-ddd-modeling/mda-003-platform-specific-model-rubric.json",
      "artifact_level_check_count": 18,
      "critic_seat_count": 3,
      "critic_seat_check_count": 45,
      "total_check_count": 63
    },
    {
      "artifact_id": "MDA-004",
      "artifact_name": "Model Transformation Record",
      "family": "mda-ddd-modeling",
      "rubric_md": "mda-ddd-modeling/mda-004-model-transformation-record-rubric.md",
      "rubric_json": "mda-ddd-modeling/mda-004-model-transformation-record-rubric.json",
      "artifact_level_check_count": 18,
      "critic_seat_count": 3,
      "critic_seat_check_count": 45,
      "total_check_count": 63
    },
    {
      "artifact_id": "DDD-001",
      "artifact_name": "Bounded Context Map",
      "family": "mda-ddd-modeling",
      "rubric_md": "mda-ddd-modeling/ddd-001-bounded-context-map-rubric.md",
      "rubric_json": "mda-ddd-modeling/ddd-001-bounded-context-map-rubric.json",
      "artifact_level_check_count": 18,
      "critic_seat_count": 3,
      "critic_seat_check_count": 45,
      "total_check_count": 63
    },
    {
      "artifact_id": "DDD-002",
      "artifact_name": "Aggregate and Invariant Catalog",
      "family": "mda-ddd-modeling",
      "rubric_md": "mda-ddd-modeling/ddd-002-aggregate-and-invariant-catalog-rubric.md",
      "rubric_json": "mda-ddd-modeling/ddd-002-aggregate-and-invariant-catalog-rubric.json",
      "artifact_level_check_count": 18,
      "critic_seat_count": 3,
      "critic_seat_check_count": 45,
      "total_check_count": 63
    },
    {
      "artifact_id": "DDD-003",
      "artifact_name": "Anti-Corruption Layer Plan",
      "family": "mda-ddd-modeling",
      "rubric_md": "mda-ddd-modeling/ddd-003-anti-corruption-layer-plan-rubric.md",
      "rubric_json": "mda-ddd-modeling/ddd-003-anti-corruption-layer-plan-rubric.json",
      "artifact_level_check_count": 18,
      "critic_seat_count": 3,
      "critic_seat_check_count": 45,
      "total_check_count": 63
    },
    {
      "artifact_id": "IMP-001",
      "artifact_name": "Implementation Plan",
      "family": "implementation-build",
      "rubric_md": "implementation-build/imp-001-implementation-plan-rubric.md",
      "rubric_json": "implementation-build/imp-001-implementation-plan-rubric.json",
      "artifact_level_check_count": 18,
      "critic_seat_count": 3,
      "critic_seat_check_count": 45,
      "total_check_count": 63
    },
    {
      "artifact_id": "IMP-002",
      "artifact_name": "Code Change Set",
      "family": "implementation-build",
      "rubric_md": "implementation-build/imp-002-code-change-set-rubric.md",
      "rubric_json": "implementation-build/imp-002-code-change-set-rubric.json",
      "artifact_level_check_count": 18,
      "critic_seat_count": 3,
      "critic_seat_check_count": 45,
      "total_check_count": 63
    },
    {
      "artifact_id": "IMP-003",
      "artifact_name": "Build and Dependency Manifest",
      "family": "implementation-build",
      "rubric_md": "implementation-build/imp-003-build-and-dependency-manifest-rubric.md",
      "rubric_json": "implementation-build/imp-003-build-and-dependency-manifest-rubric.json",
      "artifact_level_check_count": 18,
      "critic_seat_count": 3,
      "critic_seat_check_count": 45,
      "total_check_count": 63
    },
    {
      "artifact_id": "IMP-004",
      "artifact_name": "Configuration and Environment Spec",
      "family": "implementation-build",
      "rubric_md": "implementation-build/imp-004-configuration-and-environment-spec-rubric.md",
      "rubric_json": "implementation-build/imp-004-configuration-and-environment-spec-rubric.json",
      "artifact_level_check_count": 18,
      "critic_seat_count": 3,
      "critic_seat_check_count": 45,
      "total_check_count": 63
    },
    {
      "artifact_id": "IMP-005",
      "artifact_name": "Migration and Backout Plan",
      "family": "implementation-build",
      "rubric_md": "implementation-build/imp-005-migration-and-backout-plan-rubric.md",
      "rubric_json": "implementation-build/imp-005-migration-and-backout-plan-rubric.json",
      "artifact_level_check_count": 18,
      "critic_seat_count": 3,
      "critic_seat_check_count": 45,
      "total_check_count": 63
    },
    {
      "artifact_id": "VNV-001",
      "artifact_name": "Master Test Strategy",
      "family": "verification-validation",
      "rubric_md": "verification-validation/vnv-001-master-test-strategy-rubric.md",
      "rubric_json": "verification-validation/vnv-001-master-test-strategy-rubric.json",
      "artifact_level_check_count": 18,
      "critic_seat_count": 3,
      "critic_seat_check_count": 45,
      "total_check_count": 63
    },
    {
      "artifact_id": "VNV-002",
      "artifact_name": "Test Cases and Procedures",
      "family": "verification-validation",
      "rubric_md": "verification-validation/vnv-002-test-cases-and-procedures-rubric.md",
      "rubric_json": "verification-validation/vnv-002-test-cases-and-procedures-rubric.json",
      "artifact_level_check_count": 18,
      "critic_seat_count": 3,
      "critic_seat_check_count": 45,
      "total_check_count": 63
    },
    {
      "artifact_id": "VNV-003",
      "artifact_name": "Automated Test Evidence",
      "family": "verification-validation",
      "rubric_md": "verification-validation/vnv-003-automated-test-evidence-rubric.md",
      "rubric_json": "verification-validation/vnv-003-automated-test-evidence-rubric.json",
      "artifact_level_check_count": 18,
      "critic_seat_count": 3,
      "critic_seat_check_count": 45,
      "total_check_count": 63
    },
    {
      "artifact_id": "VNV-004",
      "artifact_name": "Holdout Scenario Report",
      "family": "verification-validation",
      "rubric_md": "verification-validation/vnv-004-holdout-scenario-report-rubric.md",
      "rubric_json": "verification-validation/vnv-004-holdout-scenario-report-rubric.json",
      "artifact_level_check_count": 18,
      "critic_seat_count": 3,
      "critic_seat_check_count": 45,
      "total_check_count": 63
    },
    {
      "artifact_id": "VNV-005",
      "artifact_name": "Security Test Report",
      "family": "verification-validation",
      "rubric_md": "verification-validation/vnv-005-security-test-report-rubric.md",
      "rubric_json": "verification-validation/vnv-005-security-test-report-rubric.json",
      "artifact_level_check_count": 18,
      "critic_seat_count": 3,
      "critic_seat_check_count": 45,
      "total_check_count": 63
    },
    {
      "artifact_id": "VNV-006",
      "artifact_name": "Performance/Reliability Report",
      "family": "verification-validation",
      "rubric_md": "verification-validation/vnv-006-performance-reliability-report-rubric.md",
      "rubric_json": "verification-validation/vnv-006-performance-reliability-report-rubric.json",
      "artifact_level_check_count": 18,
      "critic_seat_count": 3,
      "critic_seat_check_count": 45,
      "total_check_count": 63
    },
    {
      "artifact_id": "VNV-007",
      "artifact_name": "Accessibility/UX Validation",
      "family": "verification-validation",
      "rubric_md": "verification-validation/vnv-007-accessibility-ux-validation-rubric.md",
      "rubric_json": "verification-validation/vnv-007-accessibility-ux-validation-rubric.json",
      "artifact_level_check_count": 18,
      "critic_seat_count": 3,
      "critic_seat_check_count": 45,
      "total_check_count": 63
    },
    {
      "artifact_id": "REL-001",
      "artifact_name": "Release Plan",
      "family": "release-production-maintenance",
      "rubric_md": "release-production-maintenance/rel-001-release-plan-rubric.md",
      "rubric_json": "release-production-maintenance/rel-001-release-plan-rubric.json",
      "artifact_level_check_count": 18,
      "critic_seat_count": 3,
      "critic_seat_check_count": 45,
      "total_check_count": 63
    },
    {
      "artifact_id": "REL-002",
      "artifact_name": "Release Notes",
      "family": "release-production-maintenance",
      "rubric_md": "release-production-maintenance/rel-002-release-notes-rubric.md",
      "rubric_json": "release-production-maintenance/rel-002-release-notes-rubric.json",
      "artifact_level_check_count": 18,
      "critic_seat_count": 3,
      "critic_seat_check_count": 45,
      "total_check_count": 63
    },
    {
      "artifact_id": "REL-003",
      "artifact_name": "Deployment Guide",
      "family": "release-production-maintenance",
      "rubric_md": "release-production-maintenance/rel-003-deployment-guide-rubric.md",
      "rubric_json": "release-production-maintenance/rel-003-deployment-guide-rubric.json",
      "artifact_level_check_count": 18,
      "critic_seat_count": 3,
      "critic_seat_check_count": 45,
      "total_check_count": 63
    },
    {
      "artifact_id": "REL-004",
      "artifact_name": "Operations Runbook",
      "family": "release-production-maintenance",
      "rubric_md": "release-production-maintenance/rel-004-operations-runbook-rubric.md",
      "rubric_json": "release-production-maintenance/rel-004-operations-runbook-rubric.json",
      "artifact_level_check_count": 18,
      "critic_seat_count": 3,
      "critic_seat_check_count": 45,
      "total_check_count": 63
    },
    {
      "artifact_id": "REL-005",
      "artifact_name": "Incident Response Guide",
      "family": "release-production-maintenance",
      "rubric_md": "release-production-maintenance/rel-005-incident-response-guide-rubric.md",
      "rubric_json": "release-production-maintenance/rel-005-incident-response-guide-rubric.json",
      "artifact_level_check_count": 18,
      "critic_seat_count": 3,
      "critic_seat_check_count": 45,
      "total_check_count": 63
    },
    {
      "artifact_id": "REL-006",
      "artifact_name": "Maintenance Guide",
      "family": "release-production-maintenance",
      "rubric_md": "release-production-maintenance/rel-006-maintenance-guide-rubric.md",
      "rubric_json": "release-production-maintenance/rel-006-maintenance-guide-rubric.json",
      "artifact_level_check_count": 18,
      "critic_seat_count": 3,
      "critic_seat_check_count": 45,
      "total_check_count": 63
    },
    {
      "artifact_id": "REL-007",
      "artifact_name": "Human Training Package",
      "family": "release-production-maintenance",
      "rubric_md": "release-production-maintenance/rel-007-human-training-package-rubric.md",
      "rubric_json": "release-production-maintenance/rel-007-human-training-package-rubric.json",
      "artifact_level_check_count": 18,
      "critic_seat_count": 3,
      "critic_seat_check_count": 45,
      "total_check_count": 63
    },
    {
      "artifact_id": "REL-008",
      "artifact_name": "Outage Drill and Operator Readiness Record",
      "family": "release-production-maintenance",
      "rubric_md": "release-production-maintenance/rel-008-outage-drill-and-operator-readiness-record-rubric.md",
      "rubric_json": "release-production-maintenance/rel-008-outage-drill-and-operator-readiness-record-rubric.json",
      "artifact_level_check_count": 18,
      "critic_seat_count": 3,
      "critic_seat_check_count": 45,
      "total_check_count": 63
    },
    {
      "artifact_id": "EVD-001",
      "artifact_name": "Bidirectional Traceability Matrix",
      "family": "evidence-certification",
      "rubric_md": "evidence-certification/evd-001-bidirectional-traceability-matrix-rubric.md",
      "rubric_json": "evidence-certification/evd-001-bidirectional-traceability-matrix-rubric.json",
      "artifact_level_check_count": 18,
      "critic_seat_count": 3,
      "critic_seat_check_count": 45,
      "total_check_count": 63
    },
    {
      "artifact_id": "EVD-002",
      "artifact_name": "Expert Debate Record",
      "family": "evidence-certification",
      "rubric_md": "evidence-certification/evd-002-expert-debate-record-rubric.md",
      "rubric_json": "evidence-certification/evd-002-expert-debate-record-rubric.json",
      "artifact_level_check_count": 18,
      "critic_seat_count": 3,
      "critic_seat_check_count": 45,
      "total_check_count": 63
    },
    {
      "artifact_id": "EVD-003",
      "artifact_name": "Rubric Scorecard",
      "family": "evidence-certification",
      "rubric_md": "evidence-certification/evd-003-rubric-scorecard-rubric.md",
      "rubric_json": "evidence-certification/evd-003-rubric-scorecard-rubric.json",
      "artifact_level_check_count": 18,
      "critic_seat_count": 3,
      "critic_seat_check_count": 45,
      "total_check_count": 63
    },
    {
      "artifact_id": "EVD-004",
      "artifact_name": "Quality Certificate",
      "family": "evidence-certification",
      "rubric_md": "evidence-certification/evd-004-quality-certificate-rubric.md",
      "rubric_json": "evidence-certification/evd-004-quality-certificate-rubric.json",
      "artifact_level_check_count": 18,
      "critic_seat_count": 3,
      "critic_seat_check_count": 45,
      "total_check_count": 63
    },
    {
      "artifact_id": "EVD-005",
      "artifact_name": "Provenance Record",
      "family": "evidence-certification",
      "rubric_md": "evidence-certification/evd-005-provenance-record-rubric.md",
      "rubric_json": "evidence-certification/evd-005-provenance-record-rubric.json",
      "artifact_level_check_count": 18,
      "critic_seat_count": 3,
      "critic_seat_check_count": 45,
      "total_check_count": 63
    },
    {
      "artifact_id": "EVD-006",
      "artifact_name": "Residual Risk Acceptance",
      "family": "evidence-certification",
      "rubric_md": "evidence-certification/evd-006-residual-risk-acceptance-rubric.md",
      "rubric_json": "evidence-certification/evd-006-residual-risk-acceptance-rubric.json",
      "artifact_level_check_count": 18,
      "critic_seat_count": 3,
      "critic_seat_check_count": 45,
      "total_check_count": 63
    },
    {
      "artifact_id": "EVD-007",
      "artifact_name": "Refinery Gate Record",
      "family": "evidence-certification",
      "rubric_md": "evidence-certification/evd-007-refinery-gate-record-rubric.md",
      "rubric_json": "evidence-certification/evd-007-refinery-gate-record-rubric.json",
      "artifact_level_check_count": 18,
      "critic_seat_count": 3,
      "critic_seat_check_count": 45,
      "total_check_count": 63
    },
    {
      "artifact_id": "EVD-008",
      "artifact_name": "Human Communication Record",
      "family": "evidence-certification",
      "rubric_md": "evidence-certification/evd-008-human-communication-record-rubric.md",
      "rubric_json": "evidence-certification/evd-008-human-communication-record-rubric.json",
      "artifact_level_check_count": 18,
      "critic_seat_count": 3,
      "critic_seat_check_count": 45,
      "total_check_count": 63
    },
    {
      "artifact_id": "EVD-009",
      "artifact_name": "Context Pack and Predecessor Recovery Record",
      "family": "evidence-certification",
      "rubric_md": "evidence-certification/evd-009-context-pack-and-predecessor-recovery-record-rubric.md",
      "rubric_json": "evidence-certification/evd-009-context-pack-and-predecessor-recovery-record-rubric.json",
      "artifact_level_check_count": 18,
      "critic_seat_count": 3,
      "critic_seat_check_count": 45,
      "total_check_count": 63
    },
    {
      "artifact_id": "EVD-010",
      "artifact_name": "Retrospective Learning Record",
      "family": "evidence-certification",
      "rubric_md": "evidence-certification/evd-010-retrospective-learning-record-rubric.md",
      "rubric_json": "evidence-certification/evd-010-retrospective-learning-record-rubric.json",
      "artifact_level_check_count": 18,
      "critic_seat_count": 3,
      "critic_seat_check_count": 45,
      "total_check_count": 63
    }
  ],
  "totals": {
    "artifact_level_checks": 1134,
    "critic_seat_checks": 2835,
    "total_checks": 3969
  }
}